adtpulsepy/.DS_Store
adtpulsepy/.editorconfig
adtpulsepy/__init__.py
adtpulsepy/__main__.py
adtpulsepy/exceptions.py
adtpulsepy/__pycache__/__init__.cpython-37.pyc
adtpulsepy/__pycache__/exceptions.cpython-37.pyc
adtpulsepy/devices/__init__.py
adtpulsepy/devices/alarm.py
adtpulsepy/devices/sensor.py
adtpulsepy/devices/__pycache__/__init__.cpython-37.pyc
adtpulsepy/devices/__pycache__/alarm.cpython-37.pyc
adtpulsepy/devices/__pycache__/sensor.cpython-37.pyc
adtpulsepy/helpers/__init__.py
adtpulsepy/helpers/constants.py
adtpulsepy/helpers/util.py
adtpulsepy/helpers/__pycache__/__init__.cpython-37.pyc
adtpulsepy/helpers/__pycache__/constants.cpython-37.pyc
adtpulsepy/helpers/__pycache__/util.cpython-37.pyc
adtpulsepy/tests/__init.__.py
adtpulsepy/tests/test_alarm.py
adtpulsepy/tests/__pycache__/test_alarm.cpython-37.pyc
adtpulsepy-0.0.1.dist-info/METADATA
adtpulsepy-0.0.1.dist-info/RECORD
adtpulsepy-0.0.1.dist-info/WHEEL
adtpulsepy-0.0.1.dist-info/entry_points.txt
adtpulsepy-0.0.1.dist-info/top_level.txt
